steinerpy/__init__.py
steinerpy/_version.py
steinerpy/mathematical_model.py
steinerpy/objects.py
steinerpy-0.1.3.dist-info/METADATA
steinerpy-0.1.3.dist-info/WHEEL
steinerpy-0.1.3.dist-info/licenses/LICENSE
steinerpy-0.1.3.dist-info/RECORD
