Metadata-Version: 2.4
Name: steinerpy
Version: 0.1.3
Summary: Package to solve Steiner Tree and Steiner Forest Problems with the HiGHS solver
Project-URL: Homepage, https://github.com/berendmarkhorst/SteinerPy
Project-URL: Repository, https://github.com/berendmarkhorst/SteinerPy
Project-URL: Issues, https://github.com/berendmarkhorst/SteinerPy/issues
Project-URL: Documentation, https://github.com/berendmarkhorst/SteinerPy
Project-URL: Changelog, https://github.com/berendmarkhorst/SteinerPy/releases
Author: Berend Markhorst, Joost Berkhout, Alessandro Zocca, Jeroen Pruyn, Rob van der Mei
Maintainer-email: Berend Markhorst <your.email@example.com>
License-Expression: MIT
License-File: LICENSE
Keywords: forest,graph,highs,networkx,optimization,steiner,tree
Classifier: Development Status :: 3 - Alpha
Classifier: Intended Audience :: Developers
Classifier: Intended Audience :: Science/Research
Classifier: License :: OSI Approved :: MIT License
Classifier: Programming Language :: Python :: 3
Classifier: Programming Language :: Python :: 3.8
Classifier: Programming Language :: Python :: 3.9
Classifier: Programming Language :: Python :: 3.10
Classifier: Programming Language :: Python :: 3.11
Classifier: Programming Language :: Python :: 3.12
Classifier: Topic :: Scientific/Engineering
Classifier: Topic :: Scientific/Engineering :: Mathematics
Requires-Python: >=3.8
Requires-Dist: highspy
Requires-Dist: networkx
Provides-Extra: dev
Requires-Dist: black; extra == 'dev'
Requires-Dist: flake8; extra == 'dev'
Requires-Dist: mypy; extra == 'dev'
Requires-Dist: pytest; extra == 'dev'
Requires-Dist: pytest-cov; extra == 'dev'
Provides-Extra: docs
Requires-Dist: sphinx; extra == 'docs'
Requires-Dist: sphinx-rtd-theme; extra == 'docs'
